pybragi/__init__.py
pybragi/bragi_config.py
pybragi/version.py
pybragi/analyze/num_analyzer.py
pybragi/analyze/percentile_calculator.py
pybragi/analyze/tensor_distribution.py
pybragi/base/__init__.py
pybragi/base/async_utils.py
pybragi/base/base_handler.py
pybragi/base/consul_reg.py
pybragi/base/counter.py
pybragi/base/download_utils.py
pybragi/base/gpu_detect.py
pybragi/base/hash.py
pybragi/base/image_process.py
pybragi/base/kafka_sliding.py
pybragi/base/log.py
pybragi/base/metrics.py
pybragi/base/metrics_flask.py
pybragi/base/mongo_base.py
pybragi/base/process_utils.py
pybragi/base/project_path.py
pybragi/base/ps.py
pybragi/base/scribe_log.py
pybragi/base/shutdown.py
pybragi/base/species_queue.py
pybragi/base/tail_log.py
pybragi/base/thread_bind_async_manager.py
pybragi/base/time_utils.py
pybragi/base/crypto/ase_ecb_pkcs5.py
pybragi/base/crypto/base64.py
pybragi/bench/http_prof.py
pybragi/bench/llm_openai.py
pybragi/model/audio_utils.py
pybragi/model/cache.py
pybragi/model/gpu_utils.py
pybragi/model/rwlock.py
pybragi/model/utils.py
pybragi/model/llm_api/api_demo.py
pybragi/model/llm_api/chat_completions.py
pybragi/model/llm_api/models.py
pybragi/model/ws_api/ws_infer.py
pybragi/proto/ws_audio.py
pybragi/server/dao_server_discovery.py
pybragi/server/loadbalance.py
pybragi/server/log_request.py
pybragi/store/base.py
pybragi/store/mongo_impl.py
pybragi/store/postgre_impl.py
pybragi/zy/signature.py
pybragi/zy/upload_oss.py
pybragi/zy/upload_tos.py
pybragi-0.0.21.post2.dist-info/licenses/LICENSE.txt
pybragi-0.0.21.post2.dist-info/METADATA
pybragi-0.0.21.post2.dist-info/WHEEL
pybragi-0.0.21.post2.dist-info/top_level.txt
pybragi-0.0.21.post2.dist-info/RECORD
