Metadata-Version: 2.4
Name: pybragi
Version: 0.0.21.post2
Summary: pybragi is web server framework for fast&simple usage
Author-email: DeJoker <localjie@163.com>
License-Expression: Apache-2.0
Project-URL: homepage, https://github.com/DeJoker/pybragi
Project-URL: Repository, https://github.com/DeJoker/pybragi
Classifier: Programming Language :: Python :: 3
Requires-Python: >=3.8
License-File: LICENSE.txt
Requires-Dist: pydantic
Requires-Dist: ifaddr
Requires-Dist: psutil>=5.9.1
Requires-Dist: tornado>=6.0.2
Requires-Dist: pymongo>=3.4.0
Requires-Dist: kafka-python>=2.0.2
Requires-Dist: requests>=2.22.0
Requires-Dist: prometheus_client>=0.14.1
Requires-Dist: numpy<2,>=1.25
Requires-Dist: uvicorn
Requires-Dist: nvidia-ml-py
Requires-Dist: readerwriterlock
Requires-Dist: pycryptodome
Requires-Dist: websocket-client>=1.8.0
Requires-Dist: tqdm
Requires-Dist: pycurl
Provides-Extra: audio
Requires-Dist: av>=12.0.0; extra == "audio"
Requires-Dist: librosa>=0.9.2; extra == "audio"
Requires-Dist: scipy>=1.13.0; extra == "audio"
Requires-Dist: soundfile>=0.12.1; extra == "audio"
Provides-Extra: image
Requires-Dist: opencv-python>=4.4.0; extra == "image"
Requires-Dist: pillow; extra == "image"
Provides-Extra: zy
Requires-Dist: tos>=2.8.1; extra == "zy"
Requires-Dist: volcengine>=1.0.174; extra == "zy"
Requires-Dist: facebook-scribe==2.0.post1; extra == "zy"
Requires-Dist: thrift; extra == "zy"
Provides-Extra: test
Requires-Dist: jsonlines; extra == "test"
Requires-Dist: matplotlib; extra == "test"
Requires-Dist: ujson>=1.35; extra == "test"
Provides-Extra: all
Requires-Dist: pybragi[image]; extra == "all"
Requires-Dist: pybragi[zy]; extra == "all"
Requires-Dist: pybragi[audio]; extra == "all"
Provides-Extra: dev
Requires-Dist: pybragi[all]; extra == "dev"
Requires-Dist: pybragi[test]; extra == "dev"
Dynamic: license-file
